ipysensitivityprofiler/__init__.py
ipysensitivityprofiler/_controller.py
ipysensitivityprofiler/_data.py
ipysensitivityprofiler/_model.py
ipysensitivityprofiler/_utils.py
ipysensitivityprofiler/_view.py
ipysensitivityprofiler-0.0.1.dist-info/LICENSE
ipysensitivityprofiler-0.0.1.dist-info/METADATA
ipysensitivityprofiler-0.0.1.dist-info/WHEEL
ipysensitivityprofiler-0.0.1.dist-info/top_level.txt
ipysensitivityprofiler-0.0.1.dist-info/RECORD
