Metadata-Version: 2.1
Name: ipysensitivityprofiler
Version: 0.0.1
Summary: Jupyter Widgets for visualizing local sensitivity profiles of functions.
Author-email: "Steven H. Berguin" <stevenberguin@gmail.com>
Project-URL: Homepage, https://github.com/shb84/ipysensitivityprofiler.git
Project-URL: Issues, https://github.com/shb84/ipysensitivityprofiler/issues
Classifier: Programming Language :: Python :: 3
Classifier: License :: OSI Approved :: MIT License
Classifier: Operating System :: OS Independent
Requires-Python: >=3.8
License-File: LICENSE
Requires-Dist: numpy
Requires-Dist: bqplot
Requires-Dist: jupyter
Requires-Dist: jupyterlab
Requires-Dist: traitlets
Requires-Dist: widgetsnbextension
Provides-Extra: build
Requires-Dist: build ; extra == 'build'
Requires-Dist: sphinx ; extra == 'build'
Requires-Dist: sphinx-rtd-theme ; extra == 'build'
Requires-Dist: sphinx-toolbox ; extra == 'build'
Requires-Dist: pip ; extra == 'build'
Provides-Extra: lint
Requires-Dist: black ; extra == 'lint'
Requires-Dist: docformatter ; extra == 'lint'
Requires-Dist: lxml ; extra == 'lint'
Requires-Dist: mypy ; extra == 'lint'
Requires-Dist: ruff ; extra == 'lint'
Requires-Dist: pylint ; extra == 'lint'
Provides-Extra: release
Requires-Dist: twine ; extra == 'release'
Provides-Extra: test
Requires-Dist: nbmake ; extra == 'test'
Requires-Dist: pytest ; extra == 'test'
Requires-Dist: pytest-cov ; extra == 'test'
Requires-Dist: pytest-html ; extra == 'test'
